sunodl/__init__.py
sunodl/__main__.py
sunodl/cli.py
sunodl/config.yaml
sunodl/version.py
sunodl-0.7.1.dist-info/licenses/LICENSE.txt
sunodl-0.7.1.dist-info/METADATA
sunodl-0.7.1.dist-info/WHEEL
sunodl-0.7.1.dist-info/entry_points.txt
sunodl-0.7.1.dist-info/top_level.txt
sunodl-0.7.1.dist-info/RECORD
