Metadata-Version: 2.4
Name: sunodl
Version: 0.7.1
Summary: Simple downloader for Suno songs
Author-email: Andrew Vant <ajvant@gmail.com>
License-Expression: GPL-3.0-or-later
Project-URL: Homepage, https://gitlab.com/ajvant/sunodl
Project-URL: Documentation, https://gitlab.com/ajvant/sunodl/-/blob/master/README.md
Project-URL: Repository, https://gitlab.com/ajvant/sunodl.git
Project-URL: Issues, https://gitlab.com/ajvant/sunodl/-/issues
Project-URL: Changelog, https://gitlab.com/ajvant/sunodl/-/commits/master
Keywords: suno
Classifier: Development Status :: 4 - Beta
Classifier: Intended Audience :: End Users/Desktop
Classifier: Operating System :: OS Independent
Requires-Python: >=3.9
License-File: LICENSE.txt
Requires-Dist: addict>=2
Requires-Dist: appdirs
Requires-Dist: docopt
Requires-Dist: mutagen
Requires-Dist: pyyaml>=3.10
Requires-Dist: requests
Requires-Dist: tqdm
Provides-Extra: dev
Requires-Dist: setuptools-scm>=8; extra == "dev"
Requires-Dist: wheel; extra == "dev"
Provides-Extra: test
Requires-Dist: pytest-subtests; extra == "test"
Requires-Dist: tox; extra == "test"
Dynamic: license-file
